project_management_search_utils-1.0.9.dist-info/licenses/LICENSE
project_search/__init__.py
project_search/indexing.py
project_search/permissions.py
project_search/search_service.py
project_management_search_utils-1.0.9.dist-info/METADATA
project_management_search_utils-1.0.9.dist-info/WHEEL
project_management_search_utils-1.0.9.dist-info/top_level.txt
project_management_search_utils-1.0.9.dist-info/RECORD
