Metadata-Version: 2.4
Name: project-management-search-utils
Version: 1.0.9
Summary: Django search utilities for Elasticsearch integration with permission-aware filtering
Home-page: https://github.com/paulkokos/project-management-dashboard
Author: Paul Kokos
Author-email: paulkokos@example.com
Project-URL: Bug Tracker, https://github.com/paulkokos/project-management-dashboard/issues
Project-URL: Documentation, https://github.com/paulkokos/project-management-dashboard/tree/master/packages/search-utils
Project-URL: Source Code, https://github.com/paulkokos/project-management-dashboard/tree/master/packages/search-utils
Classifier: Framework :: Django
Classifier: Framework :: Django :: 5.0
Classifier: Programming Language :: Python :: 3
Classifier: Programming Language :: Python :: 3.11
Classifier: Programming Language :: Python :: 3.12
Classifier: License :: OSI Approved :: MIT License
Classifier: Operating System :: OS Independent
Classifier: Development Status :: 5 - Production/Stable
Classifier: Intended Audience :: Developers
Classifier: Topic :: Internet :: WWW/HTTP
Requires-Python: >=3.11
License-File: LICENSE
Requires-Dist: Django>=5.0
Requires-Dist: djangorestframework>=3.14
Requires-Dist: django-haystack>=3.2
Requires-Dist: elasticsearch<9.0,>=8.0
Provides-Extra: dev
Requires-Dist: pytest>=8.0; extra == "dev"
Requires-Dist: pytest-django>=4.7; extra == "dev"
Requires-Dist: black>=23.0; extra == "dev"
Requires-Dist: flake8>=6.0; extra == "dev"
Requires-Dist: isort>=5.0; extra == "dev"
Dynamic: author
Dynamic: author-email
Dynamic: classifier
Dynamic: description
Dynamic: description-content-type
Dynamic: home-page
Dynamic: license-file
Dynamic: project-url
Dynamic: provides-extra
Dynamic: requires-dist
Dynamic: requires-python
Dynamic: summary
